{"./":{"url":"./","title":"Introduction","keywords":"","body":"Introduction Qiita dockerhub "},"md/resume.html":{"url":"md/resume.html","title":"職歴","keywords":"","body":"得意分野 Linuxサーバ設計構築 phpによるWebアプリケーションの開発 パソコンの困ったをサポート (windowsやLinux、Mac何でも可) ノウハウの記録(1200件以上) http://qiita.com/tukiyo3 Dockerの扱い https://hub.docker.com/r/tukiyo3/ 経歴 2002年 開発中のガラケーの動作テスト 業務改善: 受信数オーバー時の動作確認のため、メール1000件作成送信(becky+vbs) 2003年 商用UNIXサーバのパーティション設計、ドキュメント作成 (独学) windows, linux(LPIC Level2)の資格取得 2004年 - 2007年 サーバやネットワークの運用,監視,保守 データセンターに2交代で常駐 数千台のホスティングサーバをOSインストール(windows,solaris,linux)ラックに搭載 数百台のネットワーク機器 LANケーブル作成敷設、運用、監視 (独学) 1cd linuxのカスタマイズ,Solaris,LPIC Level3の資格取得 業務改善 ネットワーク機器の設定半自動化(TeraTermマクロ) OSインストールの自動化(1cd Linuxを使いdiskイメージ復元),Solarisのプロビジョニングインストール 環境構築の半自動化(shell script) 2007年 自社サービスのサーバ保守、社内PC準備 データセンターのサーバ保守 HDD冗長化されていなかったので対応 業務改善: OSインストールの自動化(1cd Linuxを使いdiskイメージ復元) 2008年 - 2012年 プログラム (4分の1人月) フィールド業務のすきま時間に、社内プログラマに声をかけ仕事をもらう。 簡易なページ作成、文言変更 (php(一から書く, symfony2), ASP(vbs+IIS), .net(C#)) php製オープンソースのカスタマイズ納品 (EC-CUBE) 社内掲示板 (php, mysql, postfix) (独学) iPhone3GS用アプリの開発 (Objective-C) インフラ (4分の1人月) フィールド業務のすきま時間に、社内インフラ構築 社内Webページのメンテナンス(php) 社内メールサーバ, ファイルサーバリプレース(Linux) 自社サービスの定常業務の一部を引き受ける フィールド業務 (2分の1人月) 自社サービスを日本全国のカスタマー宅内に利用いただくため ネットワーク機器、PC設置、設定、他社とのデータやりとり確認 サポート用にネットワーク図、レイアウト図の作成 業務改善 PC設定の半自動化(vbs, python, PowerShell, C, HSP) ネットワーク機器設定自動化(python) ネットワーク図、レイアウト図、作業内容の共有が今までなかったので、作成する文化を構築 図の保存用にマクロ作成(jpg化、指定場所に保存、解像度指定) すきま時間に作業内容報告を書けるようにwebページ作成(php) カスタマー情報の管理webサービス作成(php,mysql,Angularjs,bootstrap) 2013年 - 2016年現在 自社サービスのエンジニア部分を一手に引き受ける。 データセンターの機器(ネットワーク、サーバ) プログラム(不具合調査、カスタマイズ) 障害対応 自分で課題を見つけ対応 物理サーバのkvm,OpenVz化 業務改善 非エンジニアでも調査回答できるようにページ作成 (php, python, shell script, ssh) 自動巡回チェック(Selenium) ログの解析、監視、定時メール送信 社外活動 IT勉強会への参加 (自主的に発表することも) 技術情報の共有 (Qiita) スキル 業務に採用 * プログラム: php, mysql, javascript, python, vbs, vba, ruby, awk, selenium, ActiveX, sed * ネットワーク: Micro Research, Cisco, Yamaha, Juniper, Coyote Point, buffalo * ドキュメント: sphinx, pandoc, alminium(redmine), trac, wikitten, wordpress, aipo7, gitlab * ディストリ: CoreOS, archLinux, CentOS(Fedora, RHEL), Debian(Ubuntu, Linux Mint, Proxmox) * コマンドやミドルウェアなど: openssl, git, git-glow, kickstart, puppet, ansible, crond, fcron, udev, ntpd apache2.2, 2.4 mod_{ssl, user_dir, cgi, vhost_alias, setenvif, mpm_prefork, log_config, dumpio} auth_digest, LogFormat), robots.txt, squid, http_proxy, denyhosts, snmpd, sort, tig nagios(icinga), cacti, openssh, autossh, sshfs, scp, nc, authorized_keys, keychain LocalCommand, ControlMaster, dig, whois, net, mysqlbinlog, SquirrelMail, dnsbl, diskpart nmap, telnet, pathping, arp, NetworkManager ,stone, man, find, xargs, sensors, cpupower pxeboot, iPXE, yumdownloader, createrepo, srpm, checkinstall, proftpd, tenshi, rsyslog Makefile, xfs, sudo, agetty, screen, samba[34], cvs, mercurial, logrotated, date, expect ZFS, L2ARC, mdadm, devicemapper, logwatch, pflogsumm, fail2ban, bonding, bridge, htdigest colosync, heartbeat, pacemaker, pcs, drbd, nfsd, unfsd, UnixBench, virsh, pdns-recursor nestat, yes, fml, ethtool, ip, iptables dovecot, speedtest.net, xrdp, stat, vmstat postfix, djbdns, ndjbdns, procmail, mutt, imagemagick, qmail, unshadow, john, py2exe teamviewer, ntrsupport, vncviewer, tftp, phpmyadmin, etckeeper, sqlite3, grep, ipmitool kvm, OpenVz, lxc, virtualbox, vagrant, virt-manager, webvirtmgr, modern.ie, qed VBoxManage, vzmigrate, regedit, regsvr32, signtool, bcdedit, bindmount, w3m, nkf,... 業務に不採用 google app engine, Electron, golang, perl, web api, Sencha Archtect 3, CircleCI, Jenkins, zabbix, chrony docker, kinematic, Rancher, cockpit, boot2docker, docker-machine, nsenter, packer, coLinux docker-compose, fig, lxc-config, shipyard, panamax, vagrant share, vagrant cloud, xmind, boxen debootstrap, pacstrap, supermin, chroot, vsftpd, ucarp, monit, supervisord, arpwatch, watchdog AWS, lxc, vmware ESXi, AtomicHost, GCP, GMO ConoHa, jailing, systemd-nspawn, dosbox, qemu systemd, xhyve, zsh, fish, dnsmasq, rdesktop, vncserver, setxkbmap, xvfb, wkhtmltopdf pdftk, pdftotext, iat, remastersys, xfce4, cinnamon, i3, awesome, blackbox, slim, fcitx chef, itamae, capistarino3, nagircbot, keepalived, journalctl, i7, setuid, e2label, dmenu Asterisk, Twilio, slapd, SoftEther, xl2tpd, strongswan, pptpd, patch, dump, restore, tee Raspberry Pi, motion, fswebcam, vlc, diet pi, minibian, Hyperion, newsbeuter, ntsysv, omake unison, nodejs(bleesed, cheerio-httpcli, markdown-pdf, markdown2bootstrap), jq, CLEditor slack, IRC, waifu2x, wine, alsa, pulseaudio, Unity, ulimit, efibootmgr, wodim, peco, ranger odoo8, cloud9, ieserver.net, phaser, kiwi.js, tyranoscript, GitBucket, owncloud8, yo, ifttt reveal.js, yabmin, butterfly, noVNC, SendKeys, pysheng, pyside, gem, bundler, nginx, xrandr xbindkeys, xdotool, tmux, tmuxminator, byobu, Terraform, mosh, powershell, postgresql, hadoop Lodge, Heroku, sinatra, padrino, Rails, ActiveRecord, ActiveAdmin, Pydio, ddrescue, dban LVM, tcpdump, wireshark, fluentd, sensu, sandbox-exec, sixel, prelink, acpitool, wpa_supplicant AutoHotKey, BitLocker to go, sysprep, wusa, powercfg, chocolatey, cygwin, mobaxterm win2flash, glusterfs, ceph, openstack, wjoy, adb, hdiutil, diskutil, dd, arch-chroot, apt, 9p system rescue cd, clonezilla, freebsd11, tinycore, efi, grub2, parted, fdisk, gdisk, exfat fuelphp, cakephp2, IlohaMail, roundcube, xip.io, spamassassin, ffmpeg, yum-config-manager,... 興味 最新技術の体験, 仮想化 "}}